MANIFEST.in
README.rst
setup.py
socialize/.DS_Store
socialize/__init__.py
socialize/__init__.pyc
socialize/router.py
socialize/router.pyc
socialize.egg-info/PKG-INFO
socialize.egg-info/SOURCES.txt
socialize.egg-info/dependency_links.txt
socialize.egg-info/entry_points.txt
socialize.egg-info/not-zip-safe
socialize.egg-info/requires.txt
socialize.egg-info/top_level.txt
socialize/helpers/__init__.py
socialize/helpers/__init__.pyc
socialize/helpers/auth_helpers.py
socialize/helpers/auth_helpers.pyc
socialize/services/.DS_Store
socialize/services/__init__.py
socialize/services/__init__.pyc
socialize/services/auth_service.py
socialize/services/auth_service.pyc
socialize/services/finder_service.py
socialize/services/finder_service.pyc
socialize/services/group_service.py
socialize/services/group_service.pyc
socialize/services/kickstarter_service.py
socialize/services/kickstarter_service.pyc
socialize/services/message_service.py
socialize/services/message_service.pyc
socialize/services/service.py
socialize/services/service.pyc
socialize/services/shoutout_service.py
socialize/services/shoutout_service.pyc
socialize/services/status_service.py
socialize/services/status_service.pyc
socialize/services/user_service.py
socialize/services/user_service.pyc