Metadata-Version: 1.0
Name: socialize
Version: 1.0.4
Summary: The official command-line client of socialize
Home-page: http://socialize.dmonn.ch
Author: Dominic Monn
Author-email: monn.dominic@gmail.com
License: BSD
Platform: OS Independent
